[
 {
  "url_title": "Bank Card Number Recognition",
  "title": "Bank Card Number Recognition",
  "sub_title": "A method of bank card number recognition based on deep learning.",
  "top_image": "https://images.unsplash.com/photo-1553748024-d1b27fb3f960?w=1450",
  "visible": false
 },
 {
  "url_title": "LossFunction",
  "title": "目标函数",
  "sub_title": "深度学习任务中的目标函数.",
  "top_image": "https://images.unsplash.com/photo-1532618500676-2e0cbf7ba8b8?ixlib=rb-1.2.1&ixid=eyJhcHBfaWQiOjEyMDd9&auto=format&fit=crop&w=2807&q=80",
  "visible": true
 },
 {
  "url_title": "Scikit-Learn",
  "title": "Scikit-Learn",
  "sub_title": "Scikit-Learn简介.",
  "top_image": "https://images.unsplash.com/photo-1515879218367-8466d910aaa4?ixlib=rb-1.2.1&ixid=eyJhcHBfaWQiOjEyMDd9&auto=format&fit=crop&w=1950&q=80",
  "visible": true
 },
 {
  "url_title": "matplotlib",
  "title": "matplotlib",
  "sub_title": "matplotlib简介",
  "top_image": "https://images.unsplash.com/photo-1502868032459-aa78309e3503?ixlib=rb-1.2.1&ixid=eyJhcHBfaWQiOjEyMDd9&auto=format&fit=crop&w=1050&q=80",
  "visible": true
 },
 {
  "url_title": "pandas",
  "title": "pandas",
  "sub_title": "Pandas简介",
  "top_image": "https://images.unsplash.com/photo-1460925895917-afdab827c52f?ixlib=rb-1.2.1&auto=format&fit=crop&w=1002&q=80",
  "visible": true
 },
 {
  "url_title": "latex",
  "title": "LaTex",
  "sub_title": "LaTeX学习经验分享.",
  "top_image": "https://images.unsplash.com/photo-1461773518188-b3e86f98242f?ixlib=rb-1.2.1&ixid=eyJhcHBfaWQiOjEyMDd9&auto=format&fit=crop&w=1950&q=80",
  "visible": true
 },
 {
  "url_title": "clustering",
  "title": "clustering",
  "sub_title": "五种常用聚类算法",
  "top_image": "./blog/clustering/images/clustersummary.png",
  "visible": true
 },
 {
  "url_title": "meanof_",
  "title": "Python中五种下划线含义",
  "sub_title": "",
  "top_image": "https://images.unsplash.com/photo-1521249664898-864e6c1b6d5c?ixlib=rb-1.2.1&ixid=eyJhcHBfaWQiOjEyMDd9&auto=format&fit=crop&w=1950&q=80",
  "visible": true
 },
 {
  "url_title": "demo",
  "title": "demo",
  "sub_title": "A HTML Demo.",
  "top_image": "https://images.unsplash.com/photo-1553748024-d1b27fb3f960?w=1450",
  "visible": true
 },
 {
  "url_title": "funny_shots",
  "title": "funny_shots",
  "sub_title": "The world is so beautiful.",
  "top_image": "http://img1.dowebok.com/3143.png",
  "visible": true
 },
 {
  "url_title": "python_tips",
  "title": "python_tips",
  "sub_title": "Coding is an Art!",
  "top_image": "https://images.unsplash.com/photo-1526649661456-89c7ed4d00b8?ixlib=rb-1.2.1&ixid=eyJhcHBfaWQiOjEyMDd9&auto=format&fit=crop&w=2071&q=80",
  "visible": true
 },
 {
  "url_title": "python_tips_2",
  "title": "python_tips_2",
  "sub_title": "Coding is an Art!",
  "top_image": "https://images.unsplash.com/photo-1521776943084-9a3512bd6311?ixlib=rb-1.2.1&auto=format&fit=crop&w=1350&q=80",
  "visible": true
 },
 {
  "url_title": "LASSO_RIDGE",
  "title": "LASSO Regression & RIDGE Regression",
  "sub_title": "LASSO Regression & RIDGE Regression",
  "top_image": "https://images.unsplash.com/photo-1555099962-4199c345e5dd?ixlib=rb-1.2.1&ixid=eyJhcHBfaWQiOjEyMDd9&auto=format&fit=crop&w=1350&q=80",
  "visible": true
 },
 {
  "url_title": "Non_Linear_Classification",
  "title": "Non-Linear Classification",
  "sub_title": "常用的非线性分类方法.",
  "top_image": "https://images.unsplash.com/photo-1527891751199-7225231a68dd?ixlib=rb-1.2.1&ixid=eyJhcHBfaWQiOjEyMDd9&auto=format&fit=crop&w=1350&q=80",
  "visible": true
 },
 {
  "url_title": "DataExploration",
  "title": "数据探索及可视化",
  "sub_title": "Seaborn",
  "top_image": "https://images.unsplash.com/photo-1499002238440-d264edd596ec?ixlib=rb-1.2.1&ixid=eyJhcHBfaWQiOjEyMDd9&auto=format&fit=crop&w=1950&q=80",
  "visible": true
 },
 {
  "url_title": "QuantitativeVariablesPlotting",
  "title": "Some Useful Functions for Plotting Quantitative Variables",
  "sub_title": "Box Plot，Violin Plot",
  "top_image": "https://miro.medium.com/max/1673/1*m011RySTwrn3ag6XR4T-HA.png",
  "visible": true
 }
]